command_dispatcher/__init__.py
command_dispatcher/command.py
command_dispatcher/command_context.py
command_dispatcher/command_manager.py
command_dispatcher/command_source.py
command_dispatcher/arguments/__init__.py
command_dispatcher/arguments/argument_type.py
command_dispatcher/arguments/bool_argument_type.py
command_dispatcher/arguments/float_argument_type.py
command_dispatcher/arguments/integer_argument_type.py
command_dispatcher/arguments/string_argument_type.py
command_dispatcher/exceptions/__init__.py
command_dispatcher/nodes/__init__.py
command_dispatcher/nodes/argument_command_node.py
command_dispatcher/nodes/command_node.py
command_dispatcher/nodes/literal_command_node.py
command_dispatcher-0.0.3.dist-info/METADATA
command_dispatcher-0.0.3.dist-info/WHEEL
command_dispatcher-0.0.3.dist-info/licenses/LICENSE
command_dispatcher-0.0.3.dist-info/RECORD
